setup.py
finance4py/__init__.py
finance4py/backtesting.py
finance4py/instruments.py
finance4py.egg-info/PKG-INFO
finance4py.egg-info/SOURCES.txt
finance4py.egg-info/dependency_links.txt
finance4py.egg-info/requires.txt
finance4py.egg-info/top_level.txt