Metadata-Version: 1.0
Name: finance4py
Version: 0.2.2
Summary: finance analysis and backtesting tools in python
Home-page: https://github.com/m10215059/finance4py/
Author: Sheng-Huai Wang
Author-email: m10215059@csie.ntust.edu.tw
License: BSD
Platform: UNKNOWN
